verilog/src/d_latch.v
module d_latch (output q_bar, input d, input clk);
    wire w0, w1, clk_bar;

    not notCLK (clk_bar, clk);

    cmos switch1 (w0,d, clk, clk_bar);
    cmos switch2 (w0, w1, clk_bar, clk);

    not not0 (q_bar, w0);
    not not1 (w1, q_bar);
endmodule

verilog/src/d_flip_flop.v
`include "../src/d_latch.v"

module d_flip_flop (output q, input d, input clk);
    wire w1, w2, w3, clk_bar;

    // create inverted clk
    not (clk_bar, clk);

    // input not gate
    not (w1, d);

    d_latch master(w2, w1, clk_bar, clk);
    d_latch slave(w3, w2, clk, clk_bar);

    // output not gate
    not (q, w3);
endmodule

verilog/src/multiplexer/2_to_1_mux.v
`ifndef TWO_TO_ONE_MUX_V
`define TWO_TO_ONE_MUX_V

module two_to_one_mux (output q, input a, input b, input select);
    wire select_bar;

    not not0(select_bar, select);

    cmos switch0 (q, a, select, select_bar);
    cmos switch1 (q, b, select_bar, select);
endmodule

`endif // TWO_TO_ONE_MUX_V

verilog/src/1_bit_register.v
`include "../src/d_flip_flop.v"
`include "../src/2_to_1_mux.v"

module one_bit_register (output out, input in, input enable, input reset, input clk);
    wire w0, w1, w3;

    two_to_one_mux mux0 (w0, in, out, enable);

    not not0 (w1, reset);
    and and0 (w3, w0, w1);

    d_flip_flop d_flip_flop0(out, w3, clk);
endmodule

verilog/src/memory/8_bit_register.v
`include "../../src/memory/1_bit_register.v"

module eight_bit_register (output [7:0] out, input [7:0] in, input enable, input reset, input clk);
    one_bit_register reg0 (out[0], in[0], enable, reset, clk);
    one_bit_register reg1 (out[1], in[1], enable, reset, clk);
    one_bit_register reg2 (out[2], in[2], enable, reset, clk);
    one_bit_register reg3 (out[3], in[3], enable, reset, clk);
    one_bit_register reg4 (out[4], in[4], enable, reset, clk);
    one_bit_register reg5 (out[5], in[5], enable, reset, clk);
    one_bit_register reg6 (out[6], in[6], enable, reset, clk);
    one_bit_register reg7 (out[7], in[7], enable, reset, clk);
endmodule

verilog/src/8_bit_adder.v
module half_adder(a, b, sum, carry);
    input a,b;
    output sum, carry;

    xor x1(sum, a, b);
    and and1(carry, a, b);
endmodule

module full_adder(a, b, carry_in, sum, carry_out);
    input a, b, carry_in;
    output sum, carry_out;

    wire w1, w2, w3;

    half_adder half_adder1(a, b, w1, w2);
    half_adder half_adder2(w1, carry_in, sum, w3);
    or or1(carry_out, w2, w3);
endmodule

module adder_8_bit (
    input [7:0] a,
    input [7:0] b,
    output [7:0] sum,
    output carry_out
);

    wire w1, w2, w3, w4, w5, w6, w7;

    half_adder half_adder1(a[0], b[0], sum[0], w1);
    full_adder full_adder1(a[1], b[1], w1, sum[1], w2);
    full_adder full_adder2(a[2], b[2], w2, sum[2], w3);
    full_adder full_adder3(a[3], b[3], w3, sum[3], w4);
    full_adder full_adder4(a[4], b[4], w4, sum[4], w5);
    full_adder full_adder5(a[5], b[5], w5, sum[5], w6);
    full_adder full_adder6(a[6], b[6], w6, sum[6], w7);
    full_adder full_adder7(a[7], b[7], w7, sum[7], carry_out);
endmodule

verilog/testbench/memory_tb/8_bit_register_tb.v
`include "../../src/memory/8_bit_register.v"
`include "../../src/adder/8_bit_adder.v"

module eight_bit_register_tb;
    reg enable, reset, clk;
    reg [7:0] a, b; // Inputs to adder 

    wire adder_carry_out;
    wire [7:0] adder_out;
    wire [7:0] reg_out;

    adder_8_bit adder0 (a,b, adder_out, adder_carry_out);
    eight_bit_register reg8bit(reg_out, adder_out, enable, reset, clk);

    initial b = 1;
    initial a = 0;
    initial enable = 1;
    initial reset = 0;
    initial clk = 0;

    always #3 clk = ~clk;

    // The delay variables are used to randomize enable, reset, and signal a.
    reg [1:0] delay;
    reg [2:0] delay_en;
    reg [2:0] delay_reset;

    integer i;

    initial begin
        $dumpfile("eight_bit_register_sim.vcd");
        $dumpvars(0, eight_bit_register_tb);

        for(i = 0; i < 48; i = i + 1) begin
            delay = $random;
            delay_en = $random;
            delay_reset = $random;

            #(delay) a = i;
            #(delay_en) enable = ~enable;
            #(delay_reset) reset = ~reset;
        end

        #2 reset = 1;
        #10

        $finish;
    end
endmodule

verilog/testbench/memory_tb/eight_bit_register_sim.vcd
$date
	Tue Oct 24 15:55:26 2023
$end
$version
	Icarus Verilog
$end
$timescale
	1s
$end
$scope module eight_bit_register_tb $end
$var wire 8 ! reg_out [7:0] $end
$var wire 8 " adder_out [7:0] $end
$var wire 1 # adder_carry_out $end
$var reg 8 $ a [7:0] $end
$var reg 8 % b [7:0] $end
$var reg 1 & clk $end
$var reg 2 ' delay [1:0] $end
$var reg 3 ( delay_en [2:0] $end
$var reg 3 ) delay_reset [2:0] $end
$var reg 1 * enable $end
$var reg 1 + reset $end
$var integer 32 , i [31:0] $end
$scope module adder0 $end
$var wire 8 - a [7:0] $end
$var wire 8 . b [7:0] $end
$var wire 1 / w7 $end
$var wire 1 0 w6 $end
$var wire 1 1 w5 $end
$var wire 1 2 w4 $end
$var wire 1 3 w3 $end
$var wire 1 4 w2 $end
$var wire 1 5 w1 $end
$var wire 8 6 sum [7:0] $end
$var wire 1 # carry_out $end
$scope module full_adder1 $end
$var wire 1 7 a $end
$var wire 1 8 b $end
$var wire 1 4 carry_out $end
$var wire 1 9 w3 $end
$var wire 1 : w2 $end
$var wire 1 ; w1 $end
$var wire 1 < sum $end
$var wire 1 5 carry_in $end
$scope module half_adder1 $end
$var wire 1 7 a $end
$var wire 1 8 b $end
$var wire 1 : carry $end
$var wire 1 ; sum $end
$upscope $end
$scope module half_adder2 $end
$var wire 1 ; a $end
$var wire 1 9 carry $end
$var wire 1 < sum $end
$var wire 1 5 b $end
$upscope $end
$upscope $end
$scope module full_adder2 $end
$var wire 1 = a $end
$var wire 1 > b $end
$var wire 1 4 carry_in $end
$var wire 1 3 carry_out $end
$var wire 1 ? w3 $end
$var wire 1 @ w2 $end
$var wire 1 A w1 $end
$var wire 1 B sum $end
$scope module half_adder1 $end
$var wire 1 = a $end
$var wire 1 > b $end
$var wire 1 @ carry $end
$var wire 1 A sum $end
$upscope $end
$scope module half_adder2 $end
$var wire 1 A a $end
$var wire 1 4 b $end
$var wire 1 ? carry $end
$var wire 1 B sum $end
$upscope $end
$upscope $end
$scope module full_adder3 $end
$var wire 1 C a $end
$var wire 1 D b $end
$var wire 1 3 carry_in $end
$var wire 1 2 carry_out $end
$var wire 1 E w3 $end
$var wire 1 F w2 $end
$var wire 1 G w1 $end
$var wire 1 H sum $end
$scope module half_adder1 $end
$var wire 1 C a $end
$var wire 1 D b $end
$var wire 1 F carry $end
$var wire 1 G sum $end
$upscope $end
$scope module half_adder2 $end
$var wire 1 G a $end
$var wire 1 3 b $end
$var wire 1 E carry $end
$var wire 1 H sum $end
$upscope $end
$upscope $end
$scope module full_adder4 $end
$var wire 1 I a $end
$var wire 1 J b $end
$var wire 1 2 carry_in $end
$var wire 1 1 carry_out $end
$var wire 1 K w3 $end
$var wire 1 L w2 $end
$var wire 1 M w1 $end
$var wire 1 N sum $end
$scope module half_adder1 $end
$var wire 1 I a $end
$var wire 1 J b $end
$var wire 1 L carry $end
$var wire 1 M sum $end
$upscope $end
$scope module half_adder2 $end
$var wire 1 M a $end
$var wire 1 2 b $end
$var wire 1 K carry $end
$var wire 1 N sum $end
$upscope $end
$upscope $end
$scope module full_adder5 $end
$var wire 1 O a $end
$var wire 1 P b $end
$var wire 1 1 carry_in $end
$var wire 1 0 carry_out $end
$var wire 1 Q w3 $end
$var wire 1 R w2 $end
$var wire 1 S w1 $end
$var wire 1 T sum $end
$scope module half_adder1 $end
$var wire 1 O a $end
$var wire 1 P b $end
$var wire 1 R carry $end
$var wire 1 S sum $end
$upscope $end
$scope module half_adder2 $end
$var wire 1 S a $end
$var wire 1 1 b $end
$var wire 1 Q carry $end
$var wire 1 T sum $end
$upscope $end
$upscope $end
$scope module full_adder6 $end
$var wire 1 U a $end
$var wire 1 V b $end
$var wire 1 0 carry_in $end
$var wire 1 / carry_out $end
$var wire 1 W w3 $end
$var wire 1 X w2 $end
$var wire 1 Y w1 $end
$var wire 1 Z sum $end
$scope module half_adder1 $end
$var wire 1 U a $end
$var wire 1 V b $end
$var wire 1 X carry $end
$var wire 1 Y sum $end
$upscope $end
$scope module half_adder2 $end
$var wire 1 Y a $end
$var wire 1 0 b $end
$var wire 1 W carry $end
$var wire 1 Z sum $end
$upscope $end
$upscope $end
$scope module full_adder7 $end
$var wire 1 [ a $end
$var wire 1 \ b $end
$var wire 1 / carry_in $end
$var wire 1 # carry_out $end
$var wire 1 ] w3 $end
$var wire 1 ^ w2 $end
$var wire 1 _ w1 $end
$var wire 1 ` sum $end
$scope module half_adder1 $end
$var wire 1 [ a $end
$var wire 1 \ b $end
$var wire 1 ^ carry $end
$var wire 1 _ sum $end
$upscope $end
$scope module half_adder2 $end
$var wire 1 _ a $end
$var wire 1 / b $end
$var wire 1 ] carry $end
$var wire 1 ` sum $end
$upscope $end
$upscope $end
$scope module half_adder1 $end
$var wire 1 a a $end
$var wire 1 b b $end
$var wire 1 5 carry $end
$var wire 1 c sum $end
$upscope $end
$upscope $end
$scope module reg8bit $end
$var wire 1 & clk $end
$var wire 1 * enable $end
$var wire 8 d in [7:0] $end
$var wire 1 + reset $end
$var wire 8 e out [7:0] $end
$scope module reg0 $end
$var wire 1 & clk $end
$var wire 1 * enable $end
$var wire 1 f in $end
$var wire 1 + reset $end
$var wire 1 g w0 $end
$var wire 1 h w1 $end
$var wire 1 i w3 $end
$var wire 1 j out $end
$scope module d_flip_flop0 $end
$var wire 1 & clk $end
$var wire 1 k clk_bar $end
$var wire 1 i d $end
$var wire 1 j q $end
$var wire 1 l w1 $end
$var wire 1 m w3 $end
$var wire 1 n w2 $end
$scope module master $end
$var wire 1 k clk $end
$var wire 1 & clk_bar $end
$var wire 1 l d $end
$var wire 1 n q_bar $end
$var wire 1 o w0 $end
$var wire 1 p w1 $end
$upscope $end
$scope module slave $end
$var wire 1 & clk $end
$var wire 1 k clk_bar $end
$var wire 1 n d $end
$var wire 1 m q_bar $end
$var wire 1 q w0 $end
$var wire 1 r w1 $end
$upscope $end
$upscope $end
$scope module mux0 $end
$var wire 1 f a $end
$var wire 1 j b $end
$var wire 1 g q $end
$var wire 1 * select $end
$var wire 1 s select_bar $end
$upscope $end
$upscope $end
$scope module reg1 $end
$var wire 1 & clk $end
$var wire 1 * enable $end
$var wire 1 t in $end
$var wire 1 + reset $end
$var wire 1 u w0 $end
$var wire 1 v w1 $end
$var wire 1 w w3 $end
$var wire 1 x out $end
$scope module d_flip_flop0 $end
$var wire 1 & clk $end
$var wire 1 y clk_bar $end
$var wire 1 w d $end
$var wire 1 x q $end
$var wire 1 z w1 $end
$var wire 1 { w3 $end
$var wire 1 | w2 $end
$scope module master $end
$var wire 1 y clk $end
$var wire 1 & clk_bar $end
$var wire 1 z d $end
$var wire 1 | q_bar $end
$var wire 1 } w0 $end
$var wire 1 ~ w1 $end
$upscope $end
$scope module slave $end
$var wire 1 & clk $end
$var wire 1 y clk_bar $end
$var wire 1 | d $end
$var wire 1 { q_bar $end
$var wire 1 !" w0 $end
$var wire 1 "" w1 $end
$upscope $end
$upscope $end
$scope module mux0 $end
$var wire 1 t a $end
$var wire 1 x b $end
$var wire 1 u q $end
$var wire 1 * select $end
$var wire 1 #" select_bar $end
$upscope $end
$upscope $end
$scope module reg2 $end
$var wire 1 & clk $end
$var wire 1 * enable $end
$var wire 1 $" in $end
$var wire 1 + reset $end
$var wire 1 %" w0 $end
$var wire 1 &" w1 $end
$var wire 1 '" w3 $end
$var wire 1 (" out $end
$scope module d_flip_flop0 $end
$var wire 1 & clk $end
$var wire 1 )" clk_bar $end
$var wire 1 '" d $end
$var wire 1 (" q $end
$var wire 1 *" w1 $end
$var wire 1 +" w3 $end
$var wire 1 ," w2 $end
$scope module master $end
$var wire 1 )" clk $end
$var wire 1 & clk_bar $end
$var wire 1 *" d $end
$var wire 1 ," q_bar $end
$var wire 1 -" w0 $end
$var wire 1 ." w1 $end
$upscope $end
$scope module slave $end
$var wire 1 & clk $end
$var wire 1 )" clk_bar $end
$var wire 1 ," d $end
$var wire 1 +" q_bar $end
$var wire 1 /" w0 $end
$var wire 1 0" w1 $end
$upscope $end
$upscope $end
$scope module mux0 $end
$var wire 1 $" a $end
$var wire 1 (" b $end
$var wire 1 %" q $end
$var wire 1 * select $end
$var wire 1 1" select_bar $end
$upscope $end
$upscope $end
$scope module reg3 $end
$var wire 1 & clk $end
$var wire 1 * enable $end
$var wire 1 2" in $end
$var wire 1 + reset $end
$var wire 1 3" w0 $end
$var wire 1 4" w1 $end
$var wire 1 5" w3 $end
$var wire 1 6" out $end
$scope module d_flip_flop0 $end
$var wire 1 & clk $end
$var wire 1 7" clk_bar $end
$var wire 1 5" d $end
$var wire 1 6" q $end
$var wire 1 8" w1 $end
$var wire 1 9" w3 $end
$var wire 1 :" w2 $end
$scope module master $end
$var wire 1 7" clk $end
$var wire 1 & clk_bar $end
$var wire 1 8" d $end
$var wire 1 :" q_bar $end
$var wire 1 ;" w0 $end
$var wire 1 <" w1 $end
$upscope $end
$scope module slave $end
$var wire 1 & clk $end
$var wire 1 7" clk_bar $end
$var wire 1 :" d $end
$var wire 1 9" q_bar $end
$var wire 1 =" w0 $end
$var wire 1 >" w1 $end
$upscope $end
$upscope $end
$scope module mux0 $end
$var wire 1 2" a $end
$var wire 1 6" b $end
$var wire 1 3" q $end
$var wire 1 * select $end
$var wire 1 ?" select_bar $end
$upscope $end
$upscope $end
$scope module reg4 $end
$var wire 1 & clk $end
$var wire 1 * enable $end
$var wire 1 @" in $end
$var wire 1 + reset $end
$var wire 1 A" w0 $end
$var wire 1 B" w1 $end
$var wire 1 C" w3 $end
$var wire 1 D" out $end
$scope module d_flip_flop0 $end
$var wire 1 & clk $end
$var wire 1 E" clk_bar $end
$var wire 1 C" d $end
$var wire 1 D" q $end
$var wire 1 F" w1 $end
$var wire 1 G" w3 $end
$var wire 1 H" w2 $end
$scope module master $end
$var wire 1 E" clk $end
$var wire 1 & clk_bar $end
$var wire 1 F" d $end
$var wire 1 H" q_bar $end
$var wire 1 I" w0 $end
$var wire 1 J" w1 $end
$upscope $end
$scope module slave $end
$var wire 1 & clk $end
$var wire 1 E" clk_bar $end
$var wire 1 H" d $end
$var wire 1 G" q_bar $end
$var wire 1 K" w0 $end
$var wire 1 L" w1 $end
$upscope $end
$upscope $end
$scope module mux0 $end
$var wire 1 @" a $end
$var wire 1 D" b $end
$var wire 1 A" q $end
$var wire 1 * select $end
$var wire 1 M" select_bar $end
$upscope $end
$upscope $end
$scope module reg5 $end
$var wire 1 & clk $end
$var wire 1 * enable $end
$var wire 1 N" in $end
$var wire 1 + reset $end
$var wire 1 O" w0 $end
$var wire 1 P" w1 $end
$var wire 1 Q" w3 $end
$var wire 1 R" out $end
$scope module d_flip_flop0 $end
$var wire 1 & clk $end
$var wire 1 S" clk_bar $end
$var wire 1 Q" d $end
$var wire 1 R" q $end
$var wire 1 T" w1 $end
$var wire 1 U" w3 $end
$var wire 1 V" w2 $end
$scope module master $end
$var wire 1 S" clk $end
$var wire 1 & clk_bar $end
$var wire 1 T" d $end
$var wire 1 V" q_bar $end
$var wire 1 W" w0 $end
$var wire 1 X" w1 $end
$upscope $end
$scope module slave $end
$var wire 1 & clk $end
$var wire 1 S" clk_bar $end
$var wire 1 V" d $end
$var wire 1 U" q_bar $end
$var wire 1 Y" w0 $end
$var wire 1 Z" w1 $end
$upscope $end
$upscope $end
$scope module mux0 $end
$var wire 1 N" a $end
$var wire 1 R" b $end
$var wire 1 O" q $end
$var wire 1 * select $end
$var wire 1 [" select_bar $end
$upscope $end
$upscope $end
$scope module reg6 $end
$var wire 1 & clk $end
$var wire 1 * enable $end
$var wire 1 \" in $end
$var wire 1 + reset $end
$var wire 1 ]" w0 $end
$var wire 1 ^" w1 $end
$var wire 1 _" w3 $end
$var wire 1 `" out $end
$scope module d_flip_flop0 $end
$var wire 1 & clk $end
$var wire 1 a" clk_bar $end
$var wire 1 _" d $end
$var wire 1 `" q $end
$var wire 1 b" w1 $end
$var wire 1 c" w3 $end
$var wire 1 d" w2 $end
$scope module master $end
$var wire 1 a" clk $end
$var wire 1 & clk_bar $end
$var wire 1 b" d $end
$var wire 1 d" q_bar $end
$var wire 1 e" w0 $end
$var wire 1 f" w1 $end
$upscope $end
$scope module slave $end
$var wire 1 & clk $end
$var wire 1 a" clk_bar $end
$var wire 1 d" d $end
$var wire 1 c" q_bar $end
$var wire 1 g" w0 $end
$var wire 1 h" w1 $end
$upscope $end
$upscope $end
$scope module mux0 $end
$var wire 1 \" a $end
$var wire 1 `" b $end
$var wire 1 ]" q $end
$var wire 1 * select $end
$var wire 1 i" select_bar $end
$upscope $end
$upscope $end
$scope module reg7 $end
$var wire 1 & clk $end
$var wire 1 * enable $end
$var wire 1 j" in $end
$var wire 1 + reset $end
$var wire 1 k" w0 $end
$var wire 1 l" w1 $end
$var wire 1 m" w3 $end
$var wire 1 n" out $end
$scope module d_flip_flop0 $end
$var wire 1 & clk $end
$var wire 1 o" clk_bar $end
$var wire 1 m" d $end
$var wire 1 n" q $end
$var wire 1 p" w1 $end
$var wire 1 q" w3 $end
$var wire 1 r" w2 $end
$scope module master $end
$var wire 1 o" clk $end
$var wire 1 & clk_bar $end
$var wire 1 p" d $end
$var wire 1 r" q_bar $end
$var wire 1 s" w0 $end
$var wire 1 t" w1 $end
$upscope $end
$scope module slave $end
$var wire 1 & clk $end
$var wire 1 o" clk_bar $end
$var wire 1 r" d $end
$var wire 1 q" q_bar $end
$var wire 1 u" w0 $end
$var wire 1 v" w1 $end
$upscope $end
$upscope $end
$scope module mux0 $end
$var wire 1 j" a $end
$var wire 1 n" b $end
$var wire 1 k" q $end
$var wire 1 * select $end
$var wire 1 w" select_bar $end
$upscope $end
$upscope $end
$upscope $end
$upscope $end
$enddefinitions $end
$comment Show the parameter values. $end
$dumpall
$end
#0
$dumpvars
0w"
xv"
xu"
1t"
1s"
0r"
xq"
1p"
1o"
xn"
0m"
1l"
0k"
0j"
0i"
xh"
xg"
1f"
1e"
0d"
xc"
1b"
1a"
x`"
0_"
1^"
0]"
0\"
0["
xZ"
xY"
1X"
1W"
0V"
xU"
1T"
1S"
xR"
0Q"
1P"
0O"
0N"
0M"
xL"
xK"
1J"
1I"
0H"
xG"
1F"
1E"
xD"
0C"
1B"
0A"
0@"
0?"
x>"
x="
1<"
1;"
0:"
x9"
18"
17"
x6"
05"
14"
03"
02"
01"
x0"
x/"
1."
1-"
0,"
x+"
1*"
1)"
x("
0'"
1&"
0%"
0$"
0#"
x""
x!"
1~
1}
0|
x{
1z
1y
xx
0w
1v
0u
0t
0s
xr
xq
0p
0o
1n
xm
0l
1k
xj
1i
1h
1g
1f
bx e
b1 d
1c
1b
0a
0`
0_
0^
0]
0\
0[
0Z
0Y
0X
0W
0V
0U
0T
0S
0R
0Q
0P
0O
0N
0M
0L
0K
0J
0I
0H
0G
0F
0E
0D
0C
0B
0A
0@
0?
0>
0=
0<
0;
0:
09
08
07
b1 6
05
04
03
02
01
00
0/
b1 .
b0 -
b0 ,
0+
1*
b1 )
b1 (
b0 '
0&
b1 %
b0 $
0#
b1 "
bx !
$end
#1
xp
x~
x."
x<"
xJ"
xX"
xf"
xt"
xn
x|
x,"
x:"
xH"
xV"
xd"
xr"
xo
xl
x}
xz
x-"
x*"
x;"
x8"
xI"
xF"
xW"
xT"
xe"
xb"
xs"
xp"
1s
xi
1#"
xw
11"
x'"
1?"
x5"
1M"
xC"
1["
xQ"
1i"
x_"
1w"
xm"
xg
xu
x%"
x3"
xA"
xO"
x]"
xk"
0*
#2
1p
1~
1."
1<"
1J"
1X"
1f"
1t"
0n
0|
0,"
0:"
0H"
0V"
0d"
0r"
1o
1l
1}
1z
1-"
1*"
1;"
18"
1I"
1F"
1W"
1T"
1e"
1b"
1s"
1p"
0i
0w
0'"
05"
0C"
0Q"
0_"
0m"
0h
0v
0&"
04"
0B"
0P"
0^"
0l"
b101 )
b101 (
b11 '
b1 ,
1+
#3
0r
0g
0j
0""
0u
0x
00"
0%"
0("
0>"
03"
06"
0L"
0A"
0D"
0Z"
0O"
0R"
0h"
0]"
0`"
0v"
0k"
b0 !
b0 e
0n"
1m
1{
1+"
19"
1G"
1U"
1c"
1q"
0q
0k
0!"
0y
0/"
0)"
0="
07"
0K"
0E"
0Y"
0S"
0g"
0a"
0u"
0o"
1&
#5
1t
0f
1<
b10 "
b10 6
b10 d
0c
15
1a
b1 $
b1 -
#6
1k
1y
1)"
17"
1E"
1S"
1a"
1o"
0&
#9
0k
0y
0)"
07"
0E"
0S"
0a"
0o"
1&
#10
0s
0#"
01"
0?"
0M"
0["
0i"
0w"
1u
1*
#12
1k
1y
1)"
17"
1E"
1S"
1a"
1o"
0&
#15
0z
1w
0k
0y
0)"
07"
0E"
0S"
0a"
0o"
1h
1v
1&"
14"
1B"
1P"
1^"
1l"
1&
b1 )
b10 (
b1 '
b10 ,
0+
#16
0l
1i
1g
1f
b11 "
b11 6
b11 d
1c
05
1;
0a
17
b10 $
b10 -
#18
1l
1z
1p
1~
1s
0i
1#"
0w
11"
1?"
1M"
1["
1i"
1w"
1k
0q
0n
1y
0!"
0|
1)"
17"
1E"
1S"
1a"
1o"
0g
0u
0*
1o
1}
0&
#19
0h
0v
0&"
04"
0B"
0P"
0^"
0l"
b101 )
b110 (
b11 ,
1+
#20
1$"
1B
14
0t
0f
19
0<
b100 "
b100 6
b100 d
0c
15
1a
b11 $
b11 -
#21
0k
0y
0)"
07"
0E"
0S"
0a"
0o"
1&
#24
1k
1y
1)"
17"
1E"
1S"
1a"
1o"
0&
#26
0s
0#"
01"
0?"
0M"
0["
0i"
0w"
1%"
1*
#27
0k
0y
0)"
07"
0E"
0S"
0a"
0o"
1&
#30
1k
1y
1)"
17"
1E"
1S"
1a"
1o"
0&
#31
0."
1,"
0-"
0*"
1'"
1h
1v
1&"
14"
1B"
1P"
1^"
1l"
b1 )
b100 (
b100 ,
0+
#32
1<"
0:"
0."
1;"
18"
0p
1,"
05"
1n
0-"
0*"
03"
02"
0o
0l
1'"
0H
1i
04
1%"
1$"
03
1g
1f
09
1B
0?
b101 "
b101 6
b101 d
1c
05
0;
1A
0a
07
1=
b100 $
b100 -
#33
1r
1j
10"
b101 !
b101 e
1("
0k
0m
0y
0)"
0+"
07"
0E"
0S"
0a"
0o"
1q
1/"
1&
#36
1k
1y
1)"
17"
1E"
1S"
1a"
1o"
1s
1#"
11"
1?"
1M"
1["
1i"
1w"
0&
0*
#37
1p
1."
0n
0,"
1o
1l
1-"
1*"
0i
0'"
0h
0v
0&"
04"
0B"
0P"
0^"
0l"
b10 )
b101 (
b10 '
b101 ,
1+
#39
1t
0f
1<
b110 "
b110 6
b110 d
0c
15
0r
0g
0j
00"
0%"
b0 !
b0 e
0("
1a
0k
1m
0y
0)"
1+"
07"
0E"
0S"
0a"
0o"
b101 $
b101 -
0q
0/"
1&
#42
1k
1y
1)"
17"
1E"
1S"
1a"
1o"
0&
#44
0s
0#"
01"
0?"
0M"
0["
0i"
0w"
1u
1%"
1*
#45
0k
0y
0)"
07"
0E"
0S"
0a"
0o"
1&
#46
0z
0*"
1w
1'"
1h
1v
1&"
14"
1B"
1P"
1^"
1l"
b111 (
b1 '
b110 ,
0+
#47
0l
1i
1g
1f
b111 "
b111 6
b111 d
1c
05
1;
0a
17
b110 $
b110 -
#48
0p
0~
0."
1k
0q
1n
1y
0!"
1|
1)"
0/"
1,"
17"
1E"
1S"
1a"
1o"
0o
0}
0-"
0&
#51
1r
1j
1""
1x
10"
b111 !
b111 e
1("
0k
0m
0y
0{
0)"
0+"
07"
0E"
0S"
0a"
0o"
1q
1!"
1/"
1&
#54
1k
1y
1)"
17"
1E"
1S"
1a"
1o"
1s
1#"
11"
1?"
1M"
1["
1i"
1w"
0&
0*
#56
1p
1~
1."
0n
0|
0,"
1o
1l
1}
1z
1-"
1*"
0i
0w
0'"
0h
0v
0&"
04"
0B"
0P"
0^"
0l"
b110 )
b10 (
b11 '
b111 ,
1+
#57
0r
0g
0j
0""
0u
0x
00"
0%"
b0 !
b0 e
0("
0k
1m
0y
1{
0)"
1+"
07"
0E"
0S"
0a"
0o"
0q
0!"
0/"
1&
#59
12"
1H
0$"
13
0B
1?
14
0t
0f
19
0<
b1000 "
b1000 6
b1000 d
0c
15
1a
b111 $
b111 -
#60
1k
1y
1)"
17"
1E"
1S"
1a"
1o"
0&
#61
0s
0#"
01"
0?"
0M"
0["
0i"
0w"
13"
1*
#63
0k
0y
0)"
07"
0E"
0S"
0a"
0o"
1&
#66
1k
1y
1)"
17"
1E"
1S"
1a"
1o"
0&
#67
1J"
0H"
1."
1I"
1F"
0p
0,"
0C"
1n
1-"
1*"
0A"
0@"
0o
0l
0'"
0N
1i
04
0%"
0$"
03
13"
12"
02
1g
1f
09
0B
0?
1H
0E
b1001 "
b1001 6
b1001 d
1c
05
0;
0A
1G
0a
07
0=
1C
b1000 $
b1000 -
0<"
1:"
0;"
08"
15"
1h
1v
1&"
14"
1B"
1P"
1^"
1l"
b100 )
b101 (
b0 '
b1000 ,
0+
#69
1r
1j
1>"
b1001 !
b1001 e
16"
0k
0m
0y
0)"
07"
09"
0E"
0S"
0a"
0o"
1q
1="
1&
#72
1k
1y
1)"
17"
1E"
1S"
1a"
1o"
1s
1#"
11"
1?"
1M"
1["
1i"
1w"
0&
0*
#75
0k
0y
0)"
07"
0E"
0S"
0a"
0o"
1&
#76
1l
18"
0i
05"
0h
0v
0&"
04"
0B"
0P"
0^"
0l"
b101 )
b1 '
b1001 ,
1+
#77
1t
0f
1<
b1010 "
b1010 6
b1010 d
0c
15
1a
b1001 $
b1001 -
#78
1p
1<"
1k
1q
0n
1y
1)"
17"
1="
0:"
1E"
1S"
1a"
1o"
1o
1;"
0&
#81
0r
0g
0j
0>"
03"
b0 !
b0 e
06"
0k
1m
0y
0)"
07"
19"
0E"
0S"
0a"
0o"
0q
0="
1&
#82
0s
0#"
01"
0?"
0M"
0["
0i"
0w"
1u
13"
1*
#84
1k
1y
1)"
17"
1E"
1S"
1a"
1o"
0&
#87
0z
08"
1w
15"
0k
0y
0)"
07"
0E"
0S"
0a"
0o"
1h
1v
1&"
14"
1B"
1P"
1^"
1l"
1&
b0 )
b10 (
b11 '
b1010 ,
0+
#90
0p
1n
0o
0l
1i
1g
1f
0~
0<"
b1011 "
b1011 6
b1011 d
1c
05
1;
1k
1y
0!"
1|
1)"
17"
0="
1:"
1E"
1S"
1a"
1o"
0a
17
0}
0;"
0&
b1010 $
b1010 -
#92
1$"
1B
14
0t
0f
19
0<
b1100 "
b1100 6
b1100 d
0c
15
1a
b1011 $
b1011 -
0h
0v
0&"
04"
0B"
0P"
0^"
0l"
b101 )
b0 '
b1011 ,
1+
1p
1~
1<"
0n
0|
0:"
1o
1l
1}
1z
1;"
18"
1s
0i
1#"
0w
11"
1?"
05"
1M"
1["
1i"
1w"
0g
0u
03"
0*
#93
0k
0y
0)"
07"
0E"
0S"
0a"
0o"
1&
#94
0s
0#"
01"
0?"
0M"
0["
0i"
0w"
1%"
13"
1*
#96
1k
1y
1)"
17"
1E"
1S"
1a"
1o"
0&
#99
0*"
08"
1'"
15"
0k
0y
0)"
07"
0E"
0S"
0a"
0o"
1h
1v
1&"
14"
1B"
1P"
1^"
1l"
1&
b11 (
b10 '
b1100 ,
0+
#101
1F"
0C"
08"
0A"
0@"
15"
0N
0*"
13"
12"
02
0l
1'"
1H
0E
1i
04
1%"
1$"
03
1g
1f
09
1B
0?
b1101 "
b1101 6
b1101 d
1c
05
0;
1A
0a
07
1=
b1100 $
b1100 -
#102
0p
0."
0<"
1k
0q
1n
1y
1)"
0/"
1,"
17"
0="
1:"
1E"
1S"
1a"
1o"
0o
0-"
0;"
0&
#104
1p
1."
1<"
0n
0,"
0:"
1o
1l
1-"
1*"
1;"
18"
1s
0i
1#"
11"
0'"
1?"
05"
1M"
1["
1i"
1w"
0g
0%"
03"
0*
#105
0k
0y
0)"
07"
0E"
0S"
0a"
0o"
1&
#108
1k
1y
1)"
17"
1E"
1S"
1a"
1o"
0&
#109
0h
0v
0&"
04"
0B"
0P"
0^"
0l"
b11 '
b1101 ,
1+
#111
0k
0y
0)"
07"
0E"
0S"
0a"
0o"
1&
#112
1t
0f
1<
b1110 "
b1110 6
b1110 d
0c
15
1a
b1101 $
b1101 -
#114
1k
1y
1)"
17"
1E"
1S"
1a"
1o"
0&
#115
0s
0#"
01"
0?"
0M"
0["
0i"
0w"
1u
1%"
13"
1*
#117
0k
0y
0)"
07"
0E"
0S"
0a"
0o"
1&
#120
0~
0."
0<"
1|
1,"
1:"
0}
0z
0-"
0*"
0;"
08"
1w
1'"
15"
1k
1y
1)"
17"
1E"
1S"
1a"
1o"
1h
1v
1&"
14"
1B"
1P"
1^"
1l"
0&
b110 (
b10 '
b1110 ,
0+
#122
0p
1n
0o
0l
1i
1g
1f
b1111 "
b1111 6
b1111 d
1c
05
1;
0a
17
b1110 $
b1110 -
#123
1r
1j
1""
1x
10"
1("
1>"
b1111 !
b1111 e
16"
0k
0m
0y
0{
0)"
0+"
07"
09"
0E"
0S"
0a"
0o"
1q
1!"
1/"
1="
1&
#126
1k
1y
1)"
17"
1E"
1S"
1a"
1o"
0&
#128
1s
1#"
11"
1?"
1M"
1["
1i"
1w"
0*
#129
0k
0y
0)"
07"
0E"
0S"
0a"
0o"
1&
#132
1k
1y
1)"
17"
1E"
1S"
1a"
1o"
0&
