verilog/src/two_bit_multiplier.v
module two_bit_multiplier(input [1:0] a, input [1:0] b, output [3:0] out) ;
    wire w0, w1, w2, w3;

    // Stage 1
    and and0(w0, a[0], b[1]);
    and and1(out[0], a[0], b[0]);
    and and2(w1, a[1], b[0]);
    and and3(w2, a[1], b[1]);

    // Stage 2
    xor xor0(out[1], w0, w1);
    and and4(w3, w0, w1);

    // Stage 3
    xor xor1(out[2], w2, w3);
    and and5(out[3], w2, w3);
endmodule

verilog/testbench/two_bit_multiplier_tb.v
`include "../src/two_bit_multiplier.v"

module two_bit_multiplier_tb;
    reg [1:0] a, b;
    wire [3:0] out;

    two_bit_multiplier two_bit_multiplier1(a, b, out);

    integer errors;

    initial begin
        // $dumpfile("two_bit_multiplier_sim.vcd");
        // $dumpvars(0, two_bit_multiplier_tb);

        $display("Checking for errors...");
        errors = 0;

        // Check all possible 2-bit multiplications 
        for( a = 0; a < 3; a = a + 1) begin
            for( b = 0; b < 3; b = b + 1) begin
                #10; // Wait for 10 time units
                if (out != a * b) begin
                    $display("Error: %d + %d = %d", a, b, out);
                    errors = errors + 1;
                end
            end
        end

        if(errors == 0) begin
            $display("No errors found.");
        end else begin
            $display("Found %d errors.", errors);
        end
    end
endmodule

verilog/simulations/multiplier_sim/two_bit_multiplier_sim.vcd
$date
	Mon Oct 23 16:13:43 2023
$end
$version
	Icarus Verilog
$end
$timescale
	1s
$end
$scope module two_bit_multiplier_tb $end
$var wire 4 ! out [3:0] $end
$var reg 2 " a [1:0] $end
$var reg 2 # b [1:0] $end
$var integer 32 $ errors [31:0] $end
$scope module two_bit_multiplier1 $end
$var wire 2 % a [1:0] $end
$var wire 2 & b [1:0] $end
$var wire 1 ' w0 $end
$var wire 1 ( w1 $end
$var wire 1 ) w2 $end
$var wire 1 * w3 $end
$var wire 4 + out [3:0] $end
$upscope $end
$upscope $end
$enddefinitions $end
$comment Show the parameter values. $end
$dumpall
$end
#0
$dumpvars
b0 +
0*
0)
0(
0'
b0 &
b0 %
b0 $
b0 #
b0 "
b0 !
$end
#10
b1 #
b1 &
#20
b10 #
b10 &
#30
b1 "
b1 %
b0 #
b0 &
#40
b1 !
b1 +
b1 #
b1 &
#50
1'
b10 !
b10 +
b10 #
b10 &
#60
b0 !
b0 +
0'
b10 "
b10 %
b0 #
b0 &
#70
b10 !
b10 +
1(
b1 #
b1 &
#80
b100 !
b100 +
0(
1)
b10 #
b10 &
#90
1*
1'
b1001 !
b1001 +
1(
b11 "
b11 %
b11 #
b11 &
