verilog/src/multiplexer/2_to_1_mux.v
`ifndef TWO_TO_ONE_MUX_V
`define TWO_TO_ONE_MUX_V

module two_to_one_mux (output q, input a, input b, input select);
    wire select_bar;

    not not0(select_bar, select);

    cmos switch0 (q, a, select, select_bar);
    cmos switch1 (q, b, select_bar, select);
endmodule

`endif // TWO_TO_ONE_MUX_V

verilog/testbench/2_to_1_mux_tb.v
`include "../src/2_to_1_mux.v"

module two_to_one_mux_tb;
    reg a, b, select;
    wire q;

    two_to_one_mux mux (q, a, b, select);

    initial begin
        $dumpfile("two_to_one_mux_sim.vcd");
        $dumpvars(0, two_to_one_mux_tb);

        a = 0; b = 0; select = 0;
        #1
        a = 0; b = 0; select = 1;
        #1
        a = 0; b = 1; select = 0;
        #1
        a = 0; b = 1; select = 1;
        #1
        a = 1; b = 0; select = 0;
        #1
        a = 1; b = 0; select = 1;
        #1
        a = 1; b = 1; select = 0;
        #1
        a = 1; b = 1; select = 1;
    end
endmodule

verilog/testbench/two_to_one_mux_sim.vcd
$date
	Tue Oct 24 10:42:26 2023
$end
$version
	Icarus Verilog
$end
$timescale
	1s
$end
$scope module two_to_one_mux_tb $end
$var wire 1 ! q $end
$var reg 1 " a $end
$var reg 1 # b $end
$var reg 1 $ select $end
$scope module mux $end
$var wire 1 " a $end
$var wire 1 # b $end
$var wire 1 ! q $end
$var wire 1 $ select $end
$var wire 1 % select_bar $end
$upscope $end
$upscope $end
$enddefinitions $end
$comment Show the parameter values. $end
$dumpall
$end
#0
$dumpvars
1%
0$
0#
0"
0!
$end
#1
0%
1$
#2
1%
1!
0$
1#
#3
0%
0!
1$
#4
1%
0$
0#
0!
1"
#5
0%
1!
1$
#6
1%
0$
1#
#7
0%
1$
