verilog/src/8_bit_adder.v
module half_adder(a, b, sum, carry);
    input a,b;
    output sum, carry;

    xor x1(sum, a, b);
    and and1(carry, a, b);
endmodule

module full_adder(a, b, carry_in, sum, carry_out);
    input a, b, carry_in;
    output sum, carry_out;

    wire w1, w2, w3;

    half_adder half_adder1(a, b, w1, w2);
    half_adder half_adder2(w1, carry_in, sum, w3);
    or or1(carry_out, w2, w3);
endmodule

module adder_8_bit (
    input [7:0] a,
    input [7:0] b,
    output [7:0] sum,
    output carry_out
);

    wire w1, w2, w3, w4, w5, w6, w7;

    half_adder half_adder1(a[0], b[0], sum[0], w1);
    full_adder full_adder1(a[1], b[1], w1, sum[1], w2);
    full_adder full_adder2(a[2], b[2], w2, sum[2], w3);
    full_adder full_adder3(a[3], b[3], w3, sum[3], w4);
    full_adder full_adder4(a[4], b[4], w4, sum[4], w5);
    full_adder full_adder5(a[5], b[5], w5, sum[5], w6);
    full_adder full_adder6(a[6], b[6], w6, sum[6], w7);
    full_adder full_adder7(a[7], b[7], w7, sum[7], carry_out);
endmodule

verilog/testbench/full_adder_testbench.v
`include "../src/8_bit_adder.v"

module full_adder_testbench;
    reg a, b, carry_in;
    wire sum, carry_out;

    full_adder full_adder1(a, b, carry_in, sum, carry_out);

    initial begin
        $dumpfile("full_adder_simulation.vcd");
        $dumpvars(0, full_adder_testbench);

        a = 0; b = 0; carry_in = 0;
        #1
        a = 0; b = 0; carry_in = 1;
        #1
        a = 0; b = 1; carry_in = 0;
        #1
        a = 0; b = 1; carry_in = 1;
        #1
        a = 1; b = 0; carry_in = 0;
        #1
        a = 1; b = 0; carry_in = 1;
        #1
        a = 1; b = 1; carry_in = 0;
        #1
        a = 1; b = 1; carry_in = 1;
    end
endmodule

verilog/simulations/full_adder_simulation.vcd
$date
	Sat Oct 21 12:54:44 2023
$end
$version
	Icarus Verilog
$end
$timescale
	1s
$end
$scope module full_adder_testbench $end
$var wire 1 ! sum $end
$var wire 1 " carry_out $end
$var reg 1 # a $end
$var reg 1 $ b $end
$var reg 1 % carry_in $end
$scope module full_adder1 $end
$var wire 1 # a $end
$var wire 1 $ b $end
$var wire 1 % carry_in $end
$var wire 1 " carry_out $end
$var wire 1 & w3 $end
$var wire 1 ' w2 $end
$var wire 1 ( w1 $end
$var wire 1 ! sum $end
$scope module half_adder1 $end
$var wire 1 # a $end
$var wire 1 $ b $end
$var wire 1 ' carry $end
$var wire 1 ( sum $end
$upscope $end
$scope module half_adder2 $end
$var wire 1 ( a $end
$var wire 1 % b $end
$var wire 1 & carry $end
$var wire 1 ! sum $end
$upscope $end
$upscope $end
$upscope $end
$enddefinitions $end
#0
$dumpvars
0(
0'
0&
0%
0$
0#
0"
0!
$end
#1
1!
1%
#2
1(
0%
1$
#3
1"
0!
1&
1%
#4
0"
1!
0&
0%
0$
1#
#5
1"
0!
1&
1%
#6
0&
0(
1'
0%
1$
#7
1!
1%
