verilog/src/d_latch.v
module d_latch (output q_bar, input d, input clk);
    wire w0, w1, clk_bar;

    not notCLK (clk_bar, clk);

    cmos switch1 (w0,d, clk, clk_bar);
    cmos switch2 (w0, w1, clk_bar, clk);

    not not0 (q_bar, w0);
    not not1 (w1, q_bar);
endmodule

verilog/src/d_flip_flop.v
`include "../src/d_latch.v"

module d_flip_flop (output q, input d, input clk);
    wire w1, w2, w3, clk_bar;

    // create inverted clk
    not (clk_bar, clk);

    // input not gate
    not (w1, d);

    d_latch master(w2, w1, clk_bar, clk);
    d_latch slave(w3, w2, clk, clk_bar);

    // output not gate
    not (q, w3);
endmodule

verilog/src/multiplexer/2_to_1_mux.v
`ifndef TWO_TO_ONE_MUX_V
`define TWO_TO_ONE_MUX_V

module two_to_one_mux (output q, input a, input b, input select);
    wire select_bar;

    not not0(select_bar, select);

    cmos switch0 (q, a, select, select_bar);
    cmos switch1 (q, b, select_bar, select);
endmodule

`endif // TWO_TO_ONE_MUX_V

verilog/src/1_bit_register.v
`include "../src/d_flip_flop.v"
`include "../src/2_to_1_mux.v"

module one_bit_register (output out, input in, input enable, input reset, input clk);
    wire w0, w1, w3;

    two_to_one_mux mux0 (w0, in, out, enable);

    not not0 (w1, reset);
    and and0 (w3, w0, w1);

    d_flip_flop d_flip_flop0(out, w3, clk);
endmodule

verilog/testbench/1_bit_register_tb.v
`include "../src/1_bit_register.v"

module one_bit_register_tb;
    reg in, enable, reset, clk;
    wire out;

    // delay0 and delay1 are used to randomize the enable and in signals
    reg [1:0] delay0;
    reg [1:0] delay1;

    initial clk = 0;
    initial in = 0;
    initial enable = 0;
    initial reset = 1;

    one_bit_register reg0 (out, in, enable, reset, clk);

    always #3 clk = ~clk;

    integer i;

    initial begin
        $dumpfile("one_bit_register_sim.vcd");
        $dumpvars(0, one_bit_register_tb);

        #10 in = 1;
        #2 reset = 0;

        for (i = 0; i < 5; i = i + 1) begin
            delay0 = $random;
            delay1 = $random;
            #(delay0) enable = ~enable;
            #(delay1) in = i;
        end

        #2
        reset = 1;
        #5
        $finish;
    end
endmodule

verilog/simulations/one_bit_register_sim.vcd
$date
	Tue Oct 24 11:56:55 2023
$end
$version
	Icarus Verilog
$end
$timescale
	1s
$end
$scope module one_bit_register_tb $end
$var wire 1 ! out $end
$var reg 1 " clk $end
$var reg 2 # delay0 [1:0] $end
$var reg 2 $ delay1 [1:0] $end
$var reg 1 % enable $end
$var reg 1 & in $end
$var reg 1 ' reset $end
$var integer 32 ( i [31:0] $end
$scope module reg0 $end
$var wire 1 " clk $end
$var wire 1 % enable $end
$var wire 1 & in $end
$var wire 1 ' reset $end
$var wire 1 ) w0 $end
$var wire 1 * w1 $end
$var wire 1 + w3 $end
$var wire 1 ! out $end
$scope module d_flip_flop0 $end
$var wire 1 " clk $end
$var wire 1 , clk_bar $end
$var wire 1 + d $end
$var wire 1 ! q $end
$var wire 1 - w1 $end
$var wire 1 . w3 $end
$var wire 1 / w2 $end
$scope module master $end
$var wire 1 , clk $end
$var wire 1 " clk_bar $end
$var wire 1 - d $end
$var wire 1 / q_bar $end
$var wire 1 0 w0 $end
$var wire 1 1 w1 $end
$upscope $end
$scope module slave $end
$var wire 1 " clk $end
$var wire 1 , clk_bar $end
$var wire 1 / d $end
$var wire 1 . q_bar $end
$var wire 1 2 w0 $end
$var wire 1 3 w1 $end
$upscope $end
$upscope $end
$scope module mux0 $end
$var wire 1 & a $end
$var wire 1 ! b $end
$var wire 1 ) q $end
$var wire 1 % select $end
$var wire 1 4 select_bar $end
$upscope $end
$upscope $end
$upscope $end
$enddefinitions $end
$comment Show the parameter values. $end
$dumpall
$end
#0
$dumpvars
14
x3
x2
11
10
0/
x.
1-
1,
0+
0*
x)
bx (
1'
0&
0%
bx $
bx #
0"
x!
$end
#3
03
0)
0!
1.
02
0,
1"
#6
1,
0"
#9
0,
1"
#10
1&
#12
01
1/
00
0-
04
1+
1)
1%
1*
1,
b1 $
b0 #
b0 (
0'
0"
#13
11
0/
10
1-
0+
b11 $
b1 #
b1 (
0)
0&
#14
14
0%
#15
0,
1"
#17
b1 $
b10 (
1&
#18
01
1/
00
0-
04
1+
1,
1)
1%
0"
#19
11
0/
10
1-
0+
b10 $
b11 (
0)
0&
#20
14
0%
#21
0,
1"
#22
b1 $
b100 (
1&
#23
0-
04
1+
1)
1%
#24
1-
11
0+
1,
02
0/
b101 (
0)
0&
10
0"
#26
0*
1'
